redshift_client/__init__.py
redshift_client/_utils.py
redshift_client/py.typed
redshift_client/client/__init__.py
redshift_client/client/_core.py
redshift_client/client/_factory.py
redshift_client/client/_schema/__init__.py
redshift_client/client/_schema/_methods.py
redshift_client/client/_table/__init__.py
redshift_client/client/_table/_assert.py
redshift_client/client/_table/_encode.py
redshift_client/client/_table/_methods.py
redshift_client/client/_table/_new.py
redshift_client/core/__init__.py
redshift_client/core/column.py
redshift_client/core/id_objs.py
redshift_client/core/schema.py
redshift_client/core/table.py
redshift_client/core/data_type/__init__.py
redshift_client/core/data_type/alias.py
redshift_client/core/data_type/core.py
redshift_client/core/data_type/decode.py
redshift_client/sql_client/__init__.py
redshift_client/sql_client/_core/__init__.py
redshift_client/sql_client/_core/connection.py
redshift_client/sql_client/_core/cursor.py
redshift_client/sql_client/_core/primitive.py
redshift_client/sql_client/_core/query.py
redshift_client/sql_client/_factory/__init__.py
redshift_client/sql_client/_factory/_connection.py
redshift_client/sql_client/_factory/_primitive.py
redshift_client/sql_client/_factory/_temp_creds.py
redshift_client/sql_client/_factory/_cursor/__init__.py
redshift_client/sql_client/_factory/_cursor/_assert.py
redshift_client-9.0.0.dist-info/WHEEL
redshift_client-9.0.0.dist-info/METADATA
redshift_client-9.0.0.dist-info/RECORD
