Metadata-Version: 2.4
Name: redshift_client
Version: 9.0.0
Summary: Redshift client-SDK
Author-email: Product Team <development@fluidattacks.com>
Requires-Python: >=3.11
Classifier: License :: OSI Approved :: MIT License
Requires-Dist: boto3 >=1.34.131, <2.0.0
Requires-Dist: boto3-stubs >=1.34.160, <2.0.0
Requires-Dist: Deprecated >=1.2.12, <2.0.0
Requires-Dist: psycopg2 >=2.8.6, <3.0.0
Requires-Dist: fa-purity >=2.0.0, <3.0.0
Requires-Dist: mypy-boto3-redshift >=1.28.64, <2.0.0
Requires-Dist: types-Deprecated >=1.2.1, <2.0.0
Requires-Dist: types-psycopg2 >=2.9.21.10, <3.0.0
